is31fl32xx/__init__.py
is31fl32xx/is31fl32xx.py
is31fl32xx-1.3.2.dist-info/LICENSE
is31fl32xx-1.3.2.dist-info/METADATA
is31fl32xx-1.3.2.dist-info/WHEEL
is31fl32xx-1.3.2.dist-info/top_level.txt
is31fl32xx-1.3.2.dist-info/RECORD
