Metadata-Version: 2.1
Name: is31fl32xx
Version: 1.3.2
Summary: Support for the is31fl32xx LED controller
Home-page: https://github.com/matteoscordino/python-IS31FL3218-controller
Author: Matteo Scordino
License: UNKNOWN
Keywords: IS31FL3218,IS31FL3219,IS31FL32xx
Platform: UNKNOWN
Classifier: Development Status :: 5 - Production/Stable
Classifier: License :: OSI Approved :: MIT License
Classifier: Programming Language :: Python :: 3
Classifier: Programming Language :: Python :: 3.6
Classifier: Programming Language :: Python :: 3.7
Classifier: Programming Language :: Python :: 3 :: Only
Requires-Python: >=3.6, <4
License-File: LICENSE
Requires-Dist: smbus
